bda.plone.ajax-2.0.1-py3.9-nspkg.pth
bda/plone/ajax/__init__.py
bda/plone/ajax/action.py
bda/plone/ajax/batch.pt
bda/plone/ajax/batch.py
bda/plone/ajax/bda.ajax.pt
bda/plone/ajax/configure.zcml
bda/plone/ajax/form.py
bda/plone/ajax/i18n.sh
bda/plone/ajax/interfaces.py
bda/plone/ajax/profile.zcml
bda/plone/ajax/setuphandlers.py
bda/plone/ajax/utils.py
bda/plone/ajax/examples/__init__.py
bda/plone/ajax/examples/ajaxform.pt
bda/plone/ajax/examples/ajaxform.py
bda/plone/ajax/examples/ajaxformview.pt
bda/plone/ajax/examples/ajaxoverlayformview.pt
bda/plone/ajax/examples/batchedresult.pt
bda/plone/ajax/examples/batchview.pt
bda/plone/ajax/examples/configure.zcml
bda/plone/ajax/examples/examplebatch.py
bda/plone/ajax/examples/ploneview.pt
bda/plone/ajax/examples/provider.py
bda/plone/ajax/examples/tile_a.pt
bda/plone/ajax/examples/tile_b.pt
bda/plone/ajax/locales/bda.plone.ajax.pot
bda/plone/ajax/locales/de/LC_MESSAGES/bda.plone.ajax.po
bda/plone/ajax/locales/en/LC_MESSAGES/bda.plone.ajax.po
bda/plone/ajax/profile/default/browserlayer.xml
bda/plone/ajax/profile/default/metadata.xml
bda/plone/ajax/profile/default/registry.xml
bda/plone/ajax/profile/uninstall/browserlayer.xml
bda/plone/ajax/profile/uninstall/registry.xml
bda/plone/ajax/resources/jquerytools-custom.js
bda.plone.ajax-2.0.1.dist-info/LICENSE.rst
bda.plone.ajax-2.0.1.dist-info/METADATA
bda.plone.ajax-2.0.1.dist-info/WHEEL
bda.plone.ajax-2.0.1.dist-info/entry_points.txt
bda.plone.ajax-2.0.1.dist-info/namespace_packages.txt
bda.plone.ajax-2.0.1.dist-info/top_level.txt
bda.plone.ajax-2.0.1.dist-info/RECORD
