Metadata-Version: 2.1
Name: bda.plone.ajax
Version: 2.0.1
Summary: bdajax integration for Plone.
Home-page: https://pypi.org/project/bda.plone.ajax/
Author: Robert Niederreiter
Author-email: dev@bluedynamics.com
License: GNU General Public Licence
Keywords: plone ajax javascript bdajax
Classifier: Environment :: Web Environment
Classifier: Framework :: Plone
Classifier: Framework :: Plone :: Addon
Classifier: Framework :: Plone :: 5.1
Classifier: Framework :: Plone :: 5.2
Classifier: Framework :: Zope :: 2
Classifier: Framework :: Zope :: 4
Classifier: Programming Language :: Python
Classifier: Programming Language :: Python :: 2.7
Classifier: Programming Language :: Python :: 3.6
Classifier: Programming Language :: Python :: 3.7
Classifier: License :: OSI Approved :: GNU General Public License (GPL)
Classifier: Operating System :: OS Independent
Classifier: Topic :: Internet :: WWW/HTTP :: Dynamic Content
License-File: LICENSE.rst
Requires-Dist: setuptools
Requires-Dist: Products.CMFPlone >=5.1
Requires-Dist: bdajax >=1.10
